pyolap/__init__.py
pyolap/pyolap.py
python_olap-0.1.1.dist-info/METADATA
python_olap-0.1.1.dist-info/WHEEL
python_olap-0.1.1.dist-info/top_level.txt
python_olap-0.1.1.dist-info/RECORD
