Metadata-Version: 2.1
Name: python-olap
Version: 0.1.1
Summary: Python for EuclidOLAP.
Home-page: https://github.com/EuclidOLAP/EuclidOLAP
Author: euclidolap
Author-email: euclidolap@outlook.com
Keywords: olap
